<?xml version="1.0" encoding="UTF-8" ?>
<rsccat version="1.0" locale="en_US" product="Simulink" xmlns:xsi="http://www.w3.org/2001/XMLSchema-instance" xsi:noNamespaceSchemaLocation="../../../../matlab/resources/schema/msgcat.xsd">
  <message>
    <entry key="BlockInCallback">Block ''{0}'' is a link and it cannot be updated from the library as one of its child blocks is in the process of executing a callback</entry>
    <entry key="CannotChangeLinkedBlkParam">Unable to change parameter ''{0}'' of block ''{1}'' because it is a linked block.</entry>
    <entry key="CaseMismatch">Block ''{0}'' refers to a library called ''{1}'' but the library in memory is called ''{2}''.  This will be an error in future releases.  Saving the model will correct the problem.</entry>
    <entry key="CircularReference">Circular reference encountered. Failed to resolve link ''{0}'' in ''{1}''</entry>
    <entry key="LibBlockNotFoundInLibrary">Could not find ''{0}'' in library ''{1}''</entry>
    <entry key="LibFailedToLoadLibrary">Failed to load library ''{0}''.</entry>
    <entry key="LinkedToAncestor">Invalid link: Library ''{0}'' is linked to parent ''{1}''</entry>
    <entry key="LockViolation">Attempt to modify ''{0}'' which is a locked (read-only) {1}</entry>
    <entry key="UnresolvedLink">Unresolved\nLink</entry>
    <entry key="MissingBlockInLib">Failed to find ''{0}'' in library ''{1}'' referenced by ''{2}''</entry>
    <entry key="MissingLibrary">Failed to load library ''{0}'' referenced by ''{1}''</entry>
    <entry key="MissingLibraryBlock">Failed to load library block ''{0}'' referenced by ''{1}''.</entry>
    <entry key="MissingSourceBlock">Reference ''{0}'' is missing SourceBlock parameter</entry>
    <entry key="ErrorInTransformationFcn">Error occurred while evaluating Transformation function ''{0}''. Block ''{1}'' is not transformed properly.</entry>
    <entry key="TransformationFcnInvalidOutputData">Invalid output data returned from Transformation function ''{0}''. Block ''{1}'' is not transformed properly.</entry>
    <entry key="TransformationFcnLibBlockPathRedefined"> Block ''{1}'' is transformed incorrectly, because the transformation function ''{0}'' contains multiple library block paths.</entry>
    <entry key="TransformationFcnLibBlockPathNotDefined"> Block ''{1}'' was transformed incorrectly because the transformation function ''{0}'' does not contain a library block path.</entry>
    <entry key="InvalidInstanceData"> Parameter ''{0}'' in InstanceData has been set with invalid value while executing Transformation function. Block ''{1}'' is not transformed properly.</entry>
    <entry key="RefModificationViolation">Attempt to modify block in a linked subsystem. This can only be done by the block or its parent through their mask initialization code</entry>
    <entry key="RefViolation">Modifying block ''{0}'' not supported.</entry>
    <entry key="WSLockViolation">Attempt to modify a read-only model workspace</entry>
    <entry key="WSLockViolationEvalIn">Unable to evaluate expression because model workspace is read-only.</entry>
    <entry key="ConfigurableSubsystem">Attempt to modify ''{0}'', which is or is
    in a configurable subsystem.</entry>

    <entry key="UnlockLibraryMessage">Attempt to modify a locked library. The action performed requires it to be unlocked.</entry>
    <entry key="Unlock">Unlock</entry>
    <entry key="DisableLink">Disable Link</entry>
    <entry key="FileChangedOnDiskPrompt">Source file of block diagram ''{0}'' has changed. Reload the block diagram before editing.</entry>
    <entry key="FileChangedOnDiskTitle">File Changed On Disk</entry>
    <entry key="LibraryBlockDisableAttempt">Attempt to modify a link. You can disable this link now and restore later if needed.</entry>

    <entry key="ModelCompiled">Attempt to modify library block or subsystem
    ''{0}'' when it is in a compiled state.</entry>

    <entry key="ReadOnlySubsystem">Attempt to modify ''{0}'', which is or is in
    a read-only subsystem.</entry>

    <entry key="InsideOrIsLockedLink">Attempt to modify a link. You cannot modify this link because it is either locked or inside another locked link.</entry>
    <entry key="SetLibraryBlockOnNonPortBlock">Library Block parameter contains library path only for Port Blocks. For non port blocks LibraryBlock cannot be set.</entry>
    <entry key="SetLibraryBlockNonEmptyReference">Setting 'LibraryBlock' parameter for resolved port blocks not supported.</entry>
    <entry key="LinkParameterizationMessage">Attempt to change parameters of a block within a link.\nThese changes can later be discarded or propagated to the library.</entry>
    <entry key="LibraryWithOldBuiltInMaskBlock">Some parameter values of block ''{0}'' are getting discarded. This block is linked to ''{1}''. Run the Upgrade Advisor on ''{2}'' to check for and update such blocks.</entry>
    <entry key="LibraryMaxWarningLimitForOldBuiltInMaskBlock">Some parameter values of block ''{0}'' are getting discarded. This block is linked to ''{1}''. Run the Upgrade Advisor on ''{2}'' to check for and update such blocks. The model may reference other such libraries. Use 'libinfo' command to identify all the referenced libraries by this model and run the Upgrade Advisor on these libraries to check for and update such blocks.</entry>
    <entry key="NoChangeWhileRunning">Changing parameter ''{0}'' of block ''{1}'' not supported during simulation.</entry>
    <entry key="CannotDisableLink">''{0}'' is a protected block. Cannot disable link to a protected block.</entry>
    <entry key="CannotModifyLockLinksToLibraryParam">''{0}'' is a protected library. Cannot change parameter 'LockLinksToLibrary'.</entry>
    <entry key="InvalidLibrary">Invalid input for library.</entry>
    <entry key="InvalidLibraryVersion">Invalid library version found in linked block ''{0}''. Link will be instantiated without using library forwarding table.</entry>
    <entry key="UnsupportedLibrary">The source library doesn't support Library Browser 2.</entry>
    <entry key="CreatePermissionDenied">Permission to create protected library ''{0}'' denied.</entry>
    <entry key="CannotCreateLibrary">Cannot create protected library ''{0}''.</entry>
    <entry key="CorruptedProtectedLibrary">''{0}'' is either corrupted or not a protected library.</entry>
    <entry key="ProtectedLibraryWrongPassword">Incorrect password for ''{0}''.</entry>
    <entry key="CannotOpenProtectedLibrary">''{0}'' is a protected library. Cannot open a protected library.</entry>
    <entry key="CannotUnlockProtectedLibrary">''{0}'' is a protected library. Cannot unlock a protected library.</entry>
    <entry key="CannotSaveProtectedLibrary">''{0}'' is a protected library. Cannot save a protected library.</entry>
  </message>
</rsccat>
